comp_dnds/__init__.py
comp_dnds/dnds.py
comp_dnds/expected.py
comp_dnds/paths.py
comp_dnds-0.2.0.dist-info/METADATA
comp_dnds-0.2.0.dist-info/WHEEL
comp_dnds-0.2.0.dist-info/RECORD
