Metadata-Version: 2.1
Name: comp_dnds
Version: 0.2.0
Summary: Efficiently computing dN/dS according to the NJ86 method
Author: maxibor
Author-email: maxime_borry@eva.mpg.de
Requires-Python: >=3.9,<3.13
Classifier: Programming Language :: Python :: 3
Classifier: Programming Language :: Python :: 3.9
Classifier: Programming Language :: Python :: 3.10
Classifier: Programming Language :: Python :: 3.11
Classifier: Programming Language :: Python :: 3.12
Requires-Dist: biopython (>=1.81,<2.0)
Requires-Dist: numpy (>=1.26.1,<2.0.0)
Requires-Dist: scipy (>=1.11.4,<2.0.0)
Requires-Dist: tqdm (>=4.66.1,<5.0.0)
